{
    "Ar36": {
        "error": 3.8382981763934794,
        "error_type": "",
        "fit": "previous",
        "references": [
            {
                "exclude": false,
                "record_id": "ba-01-N-1140"
            }
        ],
        "value": 69.07430422779126
    },
    "Ar37": {
        "error": 2.9959876508016075e-06,
        "error_type": "",
        "fit": "previous",
        "references": [
            {
                "exclude": false,
                "record_id": "ba-01-N-1140"
            }
        ],
        "value": 6.5235740247430295e-06
    },
    "Ar38": {
        "error": 2.8577102144700103e-06,
        "error_type": "",
        "fit": "previous",
        "references": [
            {
                "exclude": false,
                "record_id": "ba-01-N-1140"
            }
        ],
        "value": -7.98975985106592e-06
    },
    "Ar39": {
        "error": 2.16985821964736e-06,
        "error_type": "",
        "fit": "previous",
        "references": [
            {
                "exclude": false,
                "record_id": "ba-01-N-1140"
            }
        ],
        "value": -2.9233099901781315e-06
    },
    "Ar40": {
        "error": 4.201122811113722e-06,
        "error_type": "",
        "fit": "previous",
        "references": [
            {
                "exclude": false,
                "record_id": "ba-01-N-1140"
            }
        ],
        "value": 0.00020048352796214373
    }
}