{
    "Ar36": {
        "error": 2.9483750148225547,
        "error_type": "",
        "fit": "previous",
        "references": [
            {
                "exclude": false,
                "record_id": "ba-01-N-1311"
            }
        ],
        "value": 69.9100248036184
    },
    "Ar37": {
        "error": 2.4903748411562378e-06,
        "error_type": "",
        "fit": "previous",
        "references": [
            {
                "exclude": false,
                "record_id": "ba-01-N-1311"
            }
        ],
        "value": 1.6069387399914832e-05
    },
    "Ar38": {
        "error": 2.928550492331421e-06,
        "error_type": "",
        "fit": "previous",
        "references": [
            {
                "exclude": false,
                "record_id": "ba-01-N-1311"
            }
        ],
        "value": -1.621385758476713e-06
    },
    "Ar39": {
        "error": 2.110039259144241e-06,
        "error_type": "",
        "fit": "previous",
        "references": [
            {
                "exclude": false,
                "record_id": "ba-01-N-1311"
            }
        ],
        "value": -1.9139587939735608e-06
    },
    "Ar40": {
        "error": 4.566220901179835e-06,
        "error_type": "",
        "fit": "previous",
        "references": [
            {
                "exclude": false,
                "record_id": "ba-01-N-1311"
            }
        ],
        "value": 9.215637638319424e-05
    }
}