{
    "Ar36": {
        "error": 3.4137168505978748,
        "error_type": "",
        "fit": "previous",
        "references": [
            {
                "exclude": false,
                "record_id": "ba-01-N-1113"
            }
        ],
        "value": 78.10521380119627
    },
    "Ar37": {
        "error": 2.5600102632863756e-06,
        "error_type": "",
        "fit": "previous",
        "references": [
            {
                "exclude": false,
                "record_id": "ba-01-N-1113"
            }
        ],
        "value": 5.498159779492294e-06
    },
    "Ar38": {
        "error": 3.1232412593827304e-06,
        "error_type": "",
        "fit": "previous",
        "references": [
            {
                "exclude": false,
                "record_id": "ba-01-N-1113"
            }
        ],
        "value": 1.5267831471137316e-06
    },
    "Ar39": {
        "error": 2.4001953195915305e-06,
        "error_type": "",
        "fit": "previous",
        "references": [
            {
                "exclude": false,
                "record_id": "ba-01-N-1113"
            }
        ],
        "value": 1.264993903828656e-06
    },
    "Ar40": {
        "error": 4.151777529014203e-06,
        "error_type": "",
        "fit": "previous",
        "references": [
            {
                "exclude": false,
                "record_id": "ba-01-N-1113"
            }
        ],
        "value": 0.0002037506819486088
    }
}