{
    "Ar36": {
        "error": 0.8406072881324368,
        "error_type": "",
        "fit": "previous",
        "references": [
            {
                "exclude": false,
                "record_id": "ba-01-N-1496"
            }
        ],
        "value": 52.92836952218236
    },
    "Ar37": {
        "error": 1.6211670769484428e-07,
        "error_type": "",
        "fit": "previous",
        "references": [
            {
                "exclude": false,
                "record_id": "ba-01-N-1496"
            }
        ],
        "value": 1.0925048437020113e-05
    },
    "Ar38": {
        "error": 2.5648564676425684e-07,
        "error_type": "",
        "fit": "previous",
        "references": [
            {
                "exclude": false,
                "record_id": "ba-01-N-1496"
            }
        ],
        "value": 1.523109196833446e-07
    },
    "Ar39": {
        "error": 1.6757781296378027e-07,
        "error_type": "",
        "fit": "previous",
        "references": [
            {
                "exclude": false,
                "record_id": "ba-01-N-1496"
            }
        ],
        "value": 2.453155365967688e-06
    },
    "Ar40": {
        "error": 1.9129650125089917e-06,
        "error_type": "",
        "fit": "previous",
        "references": [
            {
                "exclude": false,
                "record_id": "ba-01-N-1496"
            }
        ],
        "value": 6.561786419318865e-05
    }
}