{
    "Ar36": {
        "error": 1.5546845790935413,
        "error_type": "",
        "fit": "previous",
        "references": [
            {
                "exclude": false,
                "record_id": "ba-01-N-1878"
            }
        ],
        "value": 312.87580871872416
    },
    "Ar37": {
        "error": 2.3649004269162902e-07,
        "error_type": "",
        "fit": "previous",
        "references": [
            {
                "exclude": false,
                "record_id": "ba-01-N-1878"
            }
        ],
        "value": 7.79425242875768e-06
    },
    "Ar38": {
        "error": 2.4469015329663907e-07,
        "error_type": "",
        "fit": "previous",
        "references": [
            {
                "exclude": false,
                "record_id": "ba-01-N-1878"
            }
        ],
        "value": 3.4669358397399556e-06
    },
    "Ar39": {
        "error": 1.6914993389231975e-07,
        "error_type": "",
        "fit": "previous",
        "references": [
            {
                "exclude": false,
                "record_id": "ba-01-N-1878"
            }
        ],
        "value": 1.6031281538496282e-06
    },
    "Ar40": {
        "error": 4.384172057493399e-06,
        "error_type": "",
        "fit": "previous",
        "references": [
            {
                "exclude": false,
                "record_id": "ba-01-N-1878"
            }
        ],
        "value": 0.001596190526763787
    }
}