{
    "Ar36": {
        "error": 2.3748359575691134,
        "error_type": "",
        "fit": "previous",
        "references": [
            {
                "exclude": false,
                "record_id": "ba-01-N-2068"
            }
        ],
        "value": 1173.3216896423628
    },
    "Ar37": {
        "error": 2.0300873137999687e-07,
        "error_type": "",
        "fit": "previous",
        "references": [
            {
                "exclude": false,
                "record_id": "ba-01-N-2068"
            }
        ],
        "value": 5.340830754584871e-06
    },
    "Ar38": {
        "error": 2.2164353466967425e-07,
        "error_type": "",
        "fit": "previous",
        "references": [
            {
                "exclude": false,
                "record_id": "ba-01-N-2068"
            }
        ],
        "value": 4.817235484596198e-06
    },
    "Ar39": {
        "error": 1.7671488207730354e-07,
        "error_type": "",
        "fit": "previous",
        "references": [
            {
                "exclude": false,
                "record_id": "ba-01-N-2068"
            }
        ],
        "value": 1.315503765453772e-06
    },
    "Ar40": {
        "error": 8.64237593306944e-06,
        "error_type": "",
        "fit": "previous",
        "references": [
            {
                "exclude": false,
                "record_id": "ba-01-N-2068"
            }
        ],
        "value": 0.005869453035273131
    }
}