{
    "Ar36": {
        "error": 0.7621033913400973,
        "error_type": "",
        "fit": "previous",
        "references": [
            {
                "exclude": false,
                "record_id": "ba-01-N-1430"
            }
        ],
        "value": 58.94719656465459
    },
    "Ar37": {
        "error": 2.4641914272428375e-07,
        "error_type": "",
        "fit": "previous",
        "references": [
            {
                "exclude": false,
                "record_id": "ba-01-N-1430"
            }
        ],
        "value": 4.537886582412719e-06
    },
    "Ar38": {
        "error": 4.283956297479082e-07,
        "error_type": "",
        "fit": "previous",
        "references": [
            {
                "exclude": false,
                "record_id": "ba-01-N-1430"
            }
        ],
        "value": 2.7989848986011e-06
    },
    "Ar39": {
        "error": 1.375346072120616e-07,
        "error_type": "",
        "fit": "previous",
        "references": [
            {
                "exclude": false,
                "record_id": "ba-01-N-1430"
            }
        ],
        "value": 3.6241847732227448e-06
    },
    "Ar40": {
        "error": 1.8710684623882625e-06,
        "error_type": "",
        "fit": "previous",
        "references": [
            {
                "exclude": false,
                "record_id": "ba-01-N-1430"
            }
        ],
        "value": 9.831436180785437e-05
    }
}