{
    "Ar36": {
        "error": 0.5804107666907558,
        "error_type": "",
        "fit": "previous",
        "references": [
            {
                "exclude": false,
                "record_id": "ba-01-N-1750"
            }
        ],
        "value": 32.14139938694667
    },
    "Ar37": {
        "error": 2.1664110592289806e-07,
        "error_type": "",
        "fit": "previous",
        "references": [
            {
                "exclude": false,
                "record_id": "ba-01-N-1750"
            }
        ],
        "value": 4.907833775796032e-06
    },
    "Ar38": {
        "error": 2.456820586045641e-07,
        "error_type": "",
        "fit": "previous",
        "references": [
            {
                "exclude": false,
                "record_id": "ba-01-N-1750"
            }
        ],
        "value": 1.5303191215476995e-06
    },
    "Ar39": {
        "error": 1.8500745032400064e-07,
        "error_type": "",
        "fit": "previous",
        "references": [
            {
                "exclude": false,
                "record_id": "ba-01-N-1750"
            }
        ],
        "value": 4.551180845474998e-06
    },
    "Ar40": {
        "error": 1.6145559653705276e-06,
        "error_type": "",
        "fit": "previous",
        "references": [
            {
                "exclude": false,
                "record_id": "ba-01-N-1750"
            }
        ],
        "value": 3.75194359422612e-05
    }
}