{
    "Ar36": {
        "error": 1.3373096272901033,
        "error_type": "",
        "fit": "previous",
        "references": [
            {
                "exclude": false,
                "record_id": "ba-01-N-3483"
            }
        ],
        "value": 176.9308112660465
    },
    "Ar37": {
        "error": 3.3780718806788863e-07,
        "error_type": "",
        "fit": "previous",
        "references": [
            {
                "exclude": false,
                "record_id": "ba-01-N-3483"
            }
        ],
        "value": 2.129365611517842e-06
    },
    "Ar38": {
        "error": 3.265601886364233e-07,
        "error_type": "",
        "fit": "previous",
        "references": [
            {
                "exclude": false,
                "record_id": "ba-01-N-3483"
            }
        ],
        "value": 9.097047286705228e-07
    },
    "Ar39": {
        "error": 2.859649239372285e-07,
        "error_type": "",
        "fit": "previous",
        "references": [
            {
                "exclude": false,
                "record_id": "ba-01-N-3483"
            }
        ],
        "value": 3.1301755276967125e-07
    },
    "Ar40": {
        "error": 4.42766009138849e-06,
        "error_type": "",
        "fit": "previous",
        "references": [
            {
                "exclude": false,
                "record_id": "ba-01-N-3483"
            }
        ],
        "value": 0.000777561501673453
    }
}